plunk/__init__.py
plunk/tw/__init__.py
plunk/tw/crude_and_selectbox_bug.py
plunk/tw/crude_and_selectbox_bug_api.py
plunk/tw/echoed_clicks.py
plunk/tw/empty_sentinel_options.py
plunk/tw/ipython_magic.py
plunk/tw/meal_preferences.txt
plunk/tw/mov_to_transcription.py
plunk/tw/potentially_useful_utils.py
plunk/tw/routing.py
plunk/tw/scrap.py
plunk/tw/scrap2.py
plunk/tw/things_decorators_break.py
plunk/tw/user_story_to_poc_demo.py
plunk/tw/front_examples/__init__.py
plunk/tw/front_examples/data_binding_1.py
plunk/tw/front_examples/make_pipelines.py
plunk/tw/front_examples/audio_ml/__init__.py
plunk/tw/front_examples/audio_ml/take01_simple_pipeline.py
plunk/tw/front_examples/audio_ml/tw_app4_drill.py
plunk/tw/front_examples/audio_ml/tw_app4_drill_components.py
plunk/tw/front_examples/crude_examples/__init__.py
plunk/tw/front_examples/crude_examples/extrude_crude_util.py
plunk/tw/front_examples/crude_examples/notebook_scrap.ipynb
plunk/tw/front_examples/crude_examples/pydantic_examples.py
plunk/tw/front_examples/crude_examples/scrap_streamlit.py
plunk/tw/front_examples/crude_examples/take_01_salary.py
plunk/tw/front_examples/crude_examples/take_02_salary.py
plunk/tw/front_examples/crude_examples/take_03_salary.py
plunk/tw/front_examples/crude_examples/take_04_model_run.py
plunk/tw/front_examples/crude_examples/take_05_model_run.py
plunk/tw/front_examples/crude_examples/take_06_model_run.py
plunk/tw/front_examples/crude_examples/take_07_model_run.py
plunk/tw/front_examples/crude_examples/take_08_model_pipe.py
plunk/tw/front_examples/crude_examples/take_09_model_pipe.py
plunk/tw/i2i_demos/__init__.py
plunk/tw/i2i_demos/demo_utils.py
plunk/tw/i2i_demos/illustrating_stories/__init__.py
plunk/tw/i2i_demos/illustrating_stories/app.py
plunk/tw/i2i_demos/illustrating_stories/configurations.py
plunk/tw/i2i_demos/illustrating_stories/resources.py
plunk/tw/i2i_demos/illustrating_stories/server.py
plunk/tw/i2i_demos/play/__init__.py
plunk/tw/i2i_demos/play/app.py
plunk-0.3.1.dist-info/METADATA
plunk-0.3.1.dist-info/WHEEL
plunk-0.3.1.dist-info/licenses/LICENSE
plunk-0.3.1.dist-info/RECORD
