Metadata-Version: 2.4
Name: plunk
Version: 0.3.1
Summary: Miscellaneous stuff I plunk here until they grow up to a repo of their own
Project-URL: Homepage, https://github.com/thorwhalen/plunk
Project-URL: Repository, https://github.com/thorwhalen/plunk
Author: Thor Whalen
License: mit
License-File: LICENSE
Requires-Python: >=3.10
